perfometrics/__init__.py
perfometrics/curl.py
perfometrics/decorators.py
perfometrics/domain_checker.py
perfometrics/status_checker.py
perfometrics-0.0.6.dist-info/LICENSE
perfometrics-0.0.6.dist-info/METADATA
perfometrics-0.0.6.dist-info/WHEEL
perfometrics-0.0.6.dist-info/top_level.txt
perfometrics-0.0.6.dist-info/RECORD
