Metadata-Version: 2.1
Name: perfometrics
Version: 0.0.6
Summary: A python library to measure the performance metrics of a website
Home-page: https://github.com/realxoman/perfometrics
Author: Ali Esmaeili
Author-email: hi@aliesm.com
Project-URL: Bug Tracker, https://github.com/realxoman/perfometrics/issues
Project-URL: Documentation, https://perfometrics.readthedocs.io/en/latest/
Keywords: performance,metrics,testing,speed test
Classifier: Programming Language :: Python :: 3
Classifier: License :: OSI Approved :: GNU General Public License v3 or later (GPLv3+)
Classifier: Operating System :: OS Independent
Requires-Python: >=3.6
License-File: LICENSE
